s2_wrapper/__init__.py
s2_wrapper/api/__init__.py
s2_wrapper/api/academic_graph/__init__.py
s2_wrapper/api/academic_graph/v1/__init__.py
s2_wrapper/api/academic_graph/v1/endpoints.py
s2_wrapper/api/academic_graph/v1/entities.py
s2_wrapper/api/base.py
s2_wrapper/api/datasets/__init__.py
s2_wrapper/api/exceptions.py
s2_wrapper/api/peer_review/__init__.py
s2_wrapper/api/recommendations/__init__.py
s2_wrapper/api/utils.py
s2_wrapper/client.py
s2_wrapper/py.typed
s2_wrapper-0.1.0.dist-info/LICENSE
s2_wrapper-0.1.0.dist-info/WHEEL
s2_wrapper-0.1.0.dist-info/METADATA
s2_wrapper-0.1.0.dist-info/RECORD
